[{"id":"376","listID":"PLs7zUO7VPyJ4DcIf9o_Rm5iJQ8iTvR_De","listName":"Deutsch lernen mit Musik (B1\/B2) | Das Bandtagebuch mit EINSHOCH6 | Willkommen bei EINSHOCH6","categoryID":"29","imageKey":"IYEZrn2uDLg","categoryName":"Advance","countVideos":"40"},{"id":"375","listID":"PLs7zUO7VPyJ5HelqCdBQpJkaPVLL5j_Lf","listName":"Miss Germany: Der Kampf um die Krone | Deutsch lernen mit Videos","categoryID":"29","imageKey":"-2qJnBKImNk","categoryName":"Advance","countVideos":"40"},{"id":"373","listID":"PLs7zUO7VPyJ6OoBNiKEClbkqO8IPA0LFj","listName":"Deutsch lernen (B2\/C1) | Erfolgreich mit Papiert\u00fcten","categoryID":"29","imageKey":"N6KFYIojCTo","categoryName":"Advance","countVideos":"37"},{"id":"372","listID":"PLs7zUO7VPyJ6xb8LXj4L99Tly2i5ZAnIR","listName":"Deutsch lernen (B2\/C1) | Die Zauberfl\u00f6te auf dem Bodensee","categoryID":"29","imageKey":"uDJB4sjxAZ8","categoryName":"Advance","countVideos":"13"},{"id":"371","listID":"PLs7zUO7VPyJ7SgtPhfS_rnlAt5QiYtwdV","listName":"Deutsch lernen (B2\/C1) | Gleiten auf Wolke sieben","categoryID":"29","imageKey":"C7-_zpbZ_W8","categoryName":"Advance","countVideos":"12"},{"id":"370","listID":"PLs7zUO7VPyJ5-E36PO-T418bxPksqxuoC","listName":"Deutsch lernen (B2\/C1) | Verteidigungsministerium in Frauenhand","categoryID":"29","imageKey":"q4V7lncKAJw","categoryName":"Advance","countVideos":"11"},{"id":"369","listID":"PLs7zUO7VPyJ4wQW9xHROMFEx3Ra0eFN4B","listName":"Die Mutter des Filterkaffees | Deutsch lernen mit Videos","categoryID":"29","imageKey":"WmTIfOV-8aI","categoryName":"Advance","countVideos":"10"},{"id":"368","listID":"PLs7zUO7VPyJ7CNZY5CSFE0drddtUgx4sG","listName":"Deutsch lernen (B2\/C1) | Wie Apps Fl\u00fcchtlingen helfen","categoryID":"29","imageKey":"VANR3D7-TdQ","categoryName":"Advance","countVideos":"7"},{"id":"367","listID":"PLs7zUO7VPyJ4C_fz9fxdf8ITU6gdQRvwj","listName":"Deutsch lernen (B2\/C1) | Wie Apps Fl\u00fcchtlingen helfen","categoryID":"29","imageKey":"VANR3D7-TdQ","categoryName":"Advance","countVideos":"5"},{"id":"366","listID":"PLs7zUO7VPyJ5xfqZjK_GxQW-RaauJCHoE","listName":"Deutsch lernen (B2\/C1) | Der Papst als Popstar","categoryID":"29","imageKey":"cjaFxxR4YIQ","categoryName":"Advance","countVideos":"7"},{"id":"365","listID":"PLs7zUO7VPyJ4t7hjeHrYCyo3LrQKeGOyX","listName":"Lesen lernen als Chance | Deutsch lernen mit Videos","categoryID":"29","imageKey":"9i6ZxDn8PN4","categoryName":"Advance","countVideos":"18"},{"id":"364","listID":"PLs7zUO7VPyJ5XMfT7pLvweRx6kHVgP_9C","listName":"Verkehrskonzepte von morgen | Deutsch lernen mit Videos","categoryID":"29","imageKey":"4uiebKvIGQw","categoryName":"Advance","countVideos":"6"},{"id":"363","listID":"PLs7zUO7VPyJ7z7FCcAeOj5g_zdI64VA_5","listName":"Deutsch lernen (B2\/C1) | Das Fest des Konsums","categoryID":"29","imageKey":"0xQaxGn-yAk","categoryName":"Advance","countVideos":"13"},{"id":"362","listID":"PLs7zUO7VPyJ6tTk_HgUDHEMn1ej5673fo","listName":"Deutsch lernen (B1\/B2) | Jojo sucht das Gl\u00fcck \u2013 Staffel 2 TRAILER 1","categoryID":"29","imageKey":"RQsatgULSqQ","categoryName":"Advance","countVideos":"33"},{"id":"361","listID":"PLs7zUO7VPyJ5q8vaO9vohSzNntbYvItJR","listName":"Deutsch lernen (B1\/B2) | Jojo sucht das Gl\u00fcck \u2013 Staffel 1 Folge 1","categoryID":"29","imageKey":"A5xmAlPXBBM","categoryName":"Advance","countVideos":"32"}]