[{"id":"7819","videoID":"pqnYBp5dmYo","videosName":"German Lesson (61) - Word Order - Part 1: Position of Main Verbs in Main Clauses - A2","videoDuration":"00:05:08","getFromList":"PL5QyCnFPRx0FJDPXNkEjOxk7jEDoQMPeX","categoryID":"6"},{"id":"7820","videoID":"jvzOl4nLKlY","videosName":"German Lesson (62) - Word Order - Part 2: Questions - A2","videoDuration":"00:05:22","getFromList":"PL5QyCnFPRx0FJDPXNkEjOxk7jEDoQMPeX","categoryID":"6"},{"id":"7821","videoID":"1TVzDdgJi4M","videosName":"German Lesson (63) - Word Order - Part 3: Time Manner Place - A2","videoDuration":"00:07:24","getFromList":"PL5QyCnFPRx0FJDPXNkEjOxk7jEDoQMPeX","categoryID":"6"},{"id":"7822","videoID":"WV4E71qaQaw","videosName":"German Lesson (110) - Subordinating Conjunctions - Part 1: weil - dass - ob - A2","videoDuration":"00:06:58","getFromList":"PL5QyCnFPRx0FJDPXNkEjOxk7jEDoQMPeX","categoryID":"6"},{"id":"7823","videoID":"4812WHY9R7Q","videosName":"German Lesson (111) - Subordinating Conjunctions - Part 2: wenn - bevor - damit - obwohl - A2","videoDuration":"00:07:18","getFromList":"PL5QyCnFPRx0FJDPXNkEjOxk7jEDoQMPeX","categoryID":"6"},{"id":"7824","videoID":"yYPd5vXqe-A","videosName":"German Lesson (112) - Subordinating Conjunctions - Part 3: wann - wo - was - wer - wie - A2","videoDuration":"00:05:42","getFromList":"PL5QyCnFPRx0FJDPXNkEjOxk7jEDoQMPeX","categoryID":"6"},{"id":"7825","videoID":"ynPiiIDjgcg","videosName":"German Lesson (67) - kein vs. nicht - A2","videoDuration":"00:19:08","getFromList":"PL5QyCnFPRx0FJDPXNkEjOxk7jEDoQMPeX","categoryID":"6"},{"id":"7826","videoID":"d6hHYEtG77A","videosName":"German Lesson (64) - Word Order - Part 4: Direct & Indirect Objects - A2","videoDuration":"00:17:56","getFromList":"PL5QyCnFPRx0FJDPXNkEjOxk7jEDoQMPeX","categoryID":"6"},{"id":"7827","videoID":"_YI4JF4Ywww","videosName":"German Lesson (128) - Subordinating Conjunctions - Part 5: Phrases with \"dass\"-clauses - A2\/B1","videoDuration":"00:04:55","getFromList":"PL5QyCnFPRx0FJDPXNkEjOxk7jEDoQMPeX","categoryID":"6"}]