[{"id":"11196","videoID":"52nLu8uDfTI","videosName":"Elder Scrolls Mythen: Abgeschworene & Die Legende des Roten Adlers","videoDuration":"00:16:13","getFromList":"PLU_VpbhGKmM83RGXMT1pLdhvCBCLV3xNz","categoryID":"31"},{"id":"11197","videoID":"LoIyXnPBCtk","videosName":"Elder Scrolls Mythen: Orks - Spielball g\u00f6ttlicher Macht","videoDuration":"00:12:34","getFromList":"PLU_VpbhGKmM83RGXMT1pLdhvCBCLV3xNz","categoryID":"31"},{"id":"11198","videoID":"fLQ3yBuM6hE","videosName":"Elder Scrolls Mythen: Argonier - Die S\u00fcndenb\u00f6cke Schwarzmarschs","videoDuration":"00:18:47","getFromList":"PLU_VpbhGKmM83RGXMT1pLdhvCBCLV3xNz","categoryID":"31"},{"id":"11199","videoID":"QQcLAPmk7Cs","videosName":"Skyrim | Drachensprache (Dovahzul) lernen","videoDuration":"00:10:52","getFromList":"PLU_VpbhGKmM83RGXMT1pLdhvCBCLV3xNz","categoryID":"31"},{"id":"11201","videoID":"kGgSBW4QHOc","videosName":"Skyrim FAQ - Eure Fragen, unsere Antworten (15): Ulfric wie Adolf Hitler?","videoDuration":"00:12:47","getFromList":"PLU_VpbhGKmM83RGXMT1pLdhvCBCLV3xNz","categoryID":"31"},{"id":"11202","videoID":"4RbSIQ44upo","videosName":"Skyrim FAQ - Eure Fragen, unsere Antworten (13): Sehr geehrter Herr MeinCraftstuff","videoDuration":"00:11:11","getFromList":"PLU_VpbhGKmM83RGXMT1pLdhvCBCLV3xNz","categoryID":"31"},{"id":"11203","videoID":"Hh6jI00dJi4","videosName":"Skyrim - Alle 24 Steine von Barenziah \/ ungew\u00f6hnliche Steine finden (Fundorte & Bedeutung)","videoDuration":"00:11:07","getFromList":"PLU_VpbhGKmM83RGXMT1pLdhvCBCLV3xNz","categoryID":"31"},{"id":"11204","videoID":"pKIfBtEu7Cs","videosName":"Skyrim Guide - Verzauberung (die st\u00e4rksten Waffen & Verzaubern leveln & Seelensteine)","videoDuration":"00:13:08","getFromList":"PLU_VpbhGKmM83RGXMT1pLdhvCBCLV3xNz","categoryID":"31"},{"id":"11205","videoID":"Q0vxbx4UQfs","videosName":"Die besten Waffen von Skyrim - Streitkolben von Molag Bal (daedrisches Artefakt)","videoDuration":"00:09:22","getFromList":"PLU_VpbhGKmM83RGXMT1pLdhvCBCLV3xNz","categoryID":"31"},{"id":"11206","videoID":"dCpuRds4Oa0","videosName":"Skyrim - Top 10 Geheimnisse, Tricks & Trivia (Teil 1)","videoDuration":"00:10:19","getFromList":"PLU_VpbhGKmM83RGXMT1pLdhvCBCLV3xNz","categoryID":"31"},{"id":"11207","videoID":"42Y1NrGVbCc","videosName":"Skyrim - Secrets, Tricks & Trivia (Teil 2) | Geheime H\u00e4user & H\u00f6hlen, Dornenherzen ohne Herz uvm...","videoDuration":"00:11:13","getFromList":"PLU_VpbhGKmM83RGXMT1pLdhvCBCLV3xNz","categoryID":"31"},{"id":"11208","videoID":"H5f5-fLatkc","videosName":"Skyrim - Secrets, Tricks & Trivia (Teil 3) | Geheime Entwicklerhalle & Betrunkene NPCs","videoDuration":"00:12:10","getFromList":"PLU_VpbhGKmM83RGXMT1pLdhvCBCLV3xNz","categoryID":"31"},{"id":"11209","videoID":"TBjdRsCkpCE","videosName":"Skyrim | Die besten (Mini-) Tipps & Tricks f\u00fcr mehr Spielspa\u00df [1]","videoDuration":"00:11:26","getFromList":"PLU_VpbhGKmM83RGXMT1pLdhvCBCLV3xNz","categoryID":"31"},{"id":"11210","videoID":"hRtJyi2eKiU","videosName":"Skyrim - Secrets, Tricks & Trivia (Teil 4) | Geheime Quests & Helgen neu aufgebaut","videoDuration":"00:11:19","getFromList":"PLU_VpbhGKmM83RGXMT1pLdhvCBCLV3xNz","categoryID":"31"},{"id":"11211","videoID":"URZ9aUN_gvg","videosName":"Skyrim | Noch mehr (Mini-) Tipps, Tricks & Glitches f\u00fcr den besten Spielspa\u00df [2]","videoDuration":"00:11:14","getFromList":"PLU_VpbhGKmM83RGXMT1pLdhvCBCLV3xNz","categoryID":"31"},{"id":"11212","videoID":"ukjRjii_htQ","videosName":"Skyrim - Secrets, Tricks & Trivia (Teil 5) | Neue Zauber & Vatermord","videoDuration":"00:10:27","getFromList":"PLU_VpbhGKmM83RGXMT1pLdhvCBCLV3xNz","categoryID":"31"},{"id":"11213","videoID":"ijpOJybtSpM","videosName":"Skyrim | Die besten (Mini-) Tipps, Tricks & Glitches f\u00fcr mehr Spielspa\u00df [3]","videoDuration":"00:12:26","getFromList":"PLU_VpbhGKmM83RGXMT1pLdhvCBCLV3xNz","categoryID":"31"},{"id":"11214","videoID":"fy7dK0Ohm50","videosName":"Skyrim FAQ - Eure Fragen, unsere Antworten (9): Kaiserstadt Easteregg und Elder Scrolls 6","videoDuration":"00:14:28","getFromList":"PLU_VpbhGKmM83RGXMT1pLdhvCBCLV3xNz","categoryID":"31"},{"id":"11215","videoID":"v3VTrcgnLPs","videosName":"Elder Scrolls Mythen: Die Dwemer (Zwerge) - Aufstieg & Untergang einer Hochkultur","videoDuration":"00:16:36","getFromList":"PLU_VpbhGKmM83RGXMT1pLdhvCBCLV3xNz","categoryID":"31"},{"id":"11216","videoID":"2_0-hM_pAaA","videosName":"Elder Scrolls Mythen: Daedra - Entstehung der geheimnisvollen Herrscher","videoDuration":"00:11:19","getFromList":"PLU_VpbhGKmM83RGXMT1pLdhvCBCLV3xNz","categoryID":"31"},{"id":"11217","videoID":"Df7q7h6ql74","videosName":"Elder Scrolls Mythen: Molag Bal & Geburt der Vampire","videoDuration":"00:10:32","getFromList":"PLU_VpbhGKmM83RGXMT1pLdhvCBCLV3xNz","categoryID":"31"},{"id":"11218","videoID":"2sH6oBsyNHg","videosName":"Elder Scrolls Mythen: Dunkle Bruderschaft - Macht durch Mord","videoDuration":"00:14:38","getFromList":"PLU_VpbhGKmM83RGXMT1pLdhvCBCLV3xNz","categoryID":"31"},{"id":"11219","videoID":"9JlcLODIpco","videosName":"Elder Scrolls Mythen: Sheogorath - Gefangen im Wahnsinn","videoDuration":"00:14:33","getFromList":"PLU_VpbhGKmM83RGXMT1pLdhvCBCLV3xNz","categoryID":"31"},{"id":"11220","videoID":"yk_VmTzC-0g","videosName":"Elder Scrolls im Spiegel der Weltgeschichte (Skyrim & Oblivion Easter Eggs)","videoDuration":"00:09:23","getFromList":"PLU_VpbhGKmM83RGXMT1pLdhvCBCLV3xNz","categoryID":"31"},{"id":"11221","videoID":"M98qHZ6h9dk","videosName":"Elder Scrolls im Spiegel der Weltgeschichte [Teil 2] -  Skyrim Easter Eggs","videoDuration":"00:10:07","getFromList":"PLU_VpbhGKmM83RGXMT1pLdhvCBCLV3xNz","categoryID":"31"},{"id":"11222","videoID":"VPHvPOJE1Uk","videosName":"Elder Scrolls Biografien | Jiub - Vom M\u00f6rder zum Held","videoDuration":"00:06:02","getFromList":"PLU_VpbhGKmM83RGXMT1pLdhvCBCLV3xNz","categoryID":"31"},{"id":"11223","videoID":"BICH9q37ewA","videosName":"Skyrim | Maiq der L\u00fcgner - Alle Zitate mit Erkl\u00e4rung [Teil 2]","videoDuration":"00:08:39","getFromList":"PLU_VpbhGKmM83RGXMT1pLdhvCBCLV3xNz","categoryID":"31"},{"id":"11224","videoID":"zjX8TGyh5mk","videosName":"Maiq der L\u00fcgner | Alle Zitate aus Oblivion mit Erkl\u00e4rung","videoDuration":"00:13:24","getFromList":"PLU_VpbhGKmM83RGXMT1pLdhvCBCLV3xNz","categoryID":"31"},{"id":"11225","videoID":"rmK4fSNXNKU","videosName":"Elder Scrolls Biografien | Gaston Bellefort - Der unerm\u00fcdliche Detektiv","videoDuration":"00:04:27","getFromList":"PLU_VpbhGKmM83RGXMT1pLdhvCBCLV3xNz","categoryID":"31"},{"id":"11226","videoID":"e8iUMF0Kj2Y","videosName":"Elder Scrolls Biografien | Crassius Curio - Strippen, Sex & Theater","videoDuration":"00:08:41","getFromList":"PLU_VpbhGKmM83RGXMT1pLdhvCBCLV3xNz","categoryID":"31"},{"id":"11227","videoID":"8j-ZGdMkeBw","videosName":"Elder Scrolls Biografien | Maiq der L\u00fcgner - Die Stimme der Spieleentwickler","videoDuration":"00:08:21","getFromList":"PLU_VpbhGKmM83RGXMT1pLdhvCBCLV3xNz","categoryID":"31"},{"id":"11228","videoID":"NE9XfFY4wng","videosName":"TESO | M\u00b4aiq der L\u00fcgner - Alle Zitate erkl\u00e4rt [Elder Scrolls Online]","videoDuration":"00:14:40","getFromList":"PLU_VpbhGKmM83RGXMT1pLdhvCBCLV3xNz","categoryID":"31"}]